{
  "project_info": {
    "project_number": "128665448166",
    "project_id": "today-15f1c",
    "storage_bucket": "today-15f1c.appspot.com"
  },
  "client": [
    {
      "client_info": {
        "mobilesdk_app_id": "1:128665448166:android:2c4b7b2082143a8cb69527",
        "android_client_info": {
          "package_name": "com.dangil.today"
        }
      },
      "oauth_client": [],
      "api_key": [
        {
          "current_key": "AIzaSyDr1brcWeHkwvjD-XVBY5bYmpJhEQI9MUc"
        }
      ],
      "services": {
        "appinvite_service": {
          "other_platform_oauth_client": []
        }
      }
    }
  ],
  "configuration_version": "1"
}